TracPendingTicket-1.2.0.dist-info/DESCRIPTION.rst
TracPendingTicket-1.2.0.dist-info/METADATA
TracPendingTicket-1.2.0.dist-info/RECORD
TracPendingTicket-1.2.0.dist-info/WHEEL
TracPendingTicket-1.2.0.dist-info/entry_points.txt
TracPendingTicket-1.2.0.dist-info/metadata.json
TracPendingTicket-1.2.0.dist-info/top_level.txt
removepending/__init__.py
removepending/remove_pending.py
