Metadata-Version: 2.0
Name: TracPendingTicket
Version: 1.2.0
Summary:     Switch from 'pending' status to a configurable status when the
Home-page: https://trac-hacks.org/wiki/PendingTicketPlugin
Author: Ryan J Ollos
Author-email: ryan.j.ollos@gmail.com
License: BSD
Keywords: trac plugin pending ticket
Platform: UNKNOWN
Classifier: Framework :: Trac
Requires-Dist: Trac
